[
  {
    "id": "ca-001",
    "slug": "canada",
    "name": "Canada",
    "flagEmoji": "🇨🇦",
    "continent": "North America",
    "lat": 56.1304,
    "lng": -106.3468,
    "currency": "CAD",
    "language": "English, French",
    "data": {
      "id": "cd-001",
      "countryId": "ca-001",
      "salarySoftwareEngineer": 95000,
      "salaryNurse": 72000,
      "salaryTeacher": 58000,
      "salaryAccountant": 65000,
      "salaryMarketingManager": 78000,
      "costRentCityCentre": 2100,
      "costRentOutside": 1550,
      "costGroceriesMonthly": 400,
      "costTransportMonthly": 120,
      "costUtilitiesMonthly": 165,
      "costEatingOut": 22,
      "scoreQualityOfLife": 8.4,
      "scoreHealthcare": 7.8,
      "scoreSafety": 8.5,
      "scoreInternetSpeed": 7.9,
      "incomeTaxRateMid": 29.32,
      "socialSecurityRate": 5.95,
      "visaDifficulty": 2,
      "visaNotes": "Express Entry is the main route for skilled workers — a points-based system (CRS score) favoring age, education, language, and experience. Current draw cutoffs sit around 480–490. Provincial Nominee Programs can significantly boost CRS scores for those targeting specific provinces.",
      "visaPopularRoutes": [
        "Express Entry (CRS)",
        "Provincial Nominee Program",
        "Global Talent Stream"
      ],
      "visaOfficialUrl": "https://www.canada.ca/en/immigration-refugees-citizenship.html",
      "moveScore": 7.8,
      "lastVerified": "2026-04-26"
    }
  },
  {
    "id": "de-001",
    "slug": "germany",
    "name": "Germany",
    "flagEmoji": "🇩🇪",
    "continent": "Europe",
    "lat": 51.1657,
    "lng": 10.4515,
    "currency": "EUR",
    "language": "German",
    "data": {
      "id": "cd-002",
      "countryId": "de-001",
      "salarySoftwareEngineer": 72000,
      "salaryNurse": 42000,
      "salaryTeacher": 55000,
      "salaryAccountant": 52000,
      "salaryMarketingManager": 62000,
      "costRentCityCentre": 1350,
      "costRentOutside": 950,
      "costGroceriesMonthly": 330,
      "costTransportMonthly": 90,
      "costUtilitiesMonthly": 280,
      "costEatingOut": 15,
      "scoreQualityOfLife": 8.1,
      "scoreHealthcare": 8.9,
      "scoreSafety": 8,
      "scoreInternetSpeed": 6.5,
      "incomeTaxRateMid": 42,
      "socialSecurityRate": 20,
      "visaDifficulty": 2,
      "visaNotes": "The EU Blue Card remains the primary route for degree-holders with a job offer (salary threshold ~€45k). The Opportunity Card (Chancenkarte), launched June 2024, lets skilled non-EU nationals enter for 12 months to job-search without a prior offer — requiring either a recognised qualification or 6 points under the points system plus proof of €1,091/month in funds.",
      "visaPopularRoutes": [
        "EU Blue Card",
        "Opportunity Card (Chancenkarte)",
        "Skilled Worker Visa"
      ],
      "visaOfficialUrl": "https://www.make-it-in-germany.com/en/",
      "moveScore": 7.2,
      "lastVerified": "2026-04-26"
    }
  },
  {
    "id": "au-001",
    "slug": "australia",
    "name": "Australia",
    "flagEmoji": "🇦🇺",
    "continent": "Oceania",
    "lat": -25.2744,
    "lng": 133.7751,
    "currency": "AUD",
    "language": "English",
    "data": {
      "id": "cd-003",
      "countryId": "au-001",
      "salarySoftwareEngineer": 110000,
      "salaryNurse": 78000,
      "salaryTeacher": 72000,
      "salaryAccountant": 75000,
      "salaryMarketingManager": 90000,
      "costRentCityCentre": 2500,
      "costRentOutside": 1800,
      "costGroceriesMonthly": 440,
      "costTransportMonthly": 155,
      "costUtilitiesMonthly": 200,
      "costEatingOut": 26,
      "scoreQualityOfLife": 8.7,
      "scoreHealthcare": 8.2,
      "scoreSafety": 8.6,
      "scoreInternetSpeed": 7.2,
      "incomeTaxRateMid": 32.5,
      "socialSecurityRate": 0,
      "visaDifficulty": 3,
      "visaNotes": "Points-based skilled migration (Subclass 189/190). Processing times have improved but remain 6–18 months depending on occupation. The Employer-Sponsored 482 visa is the fastest route for tech workers with a job offer. Critical Skills list updated regularly.",
      "visaPopularRoutes": [
        "Skilled Independent (189)",
        "Employer Sponsored (482)",
        "Global Talent (858)"
      ],
      "visaOfficialUrl": "https://immi.homeaffairs.gov.au/",
      "moveScore": 7.5,
      "lastVerified": "2026-04-26"
    }
  },
  {
    "id": "nl-001",
    "slug": "netherlands",
    "name": "Netherlands",
    "flagEmoji": "🇳🇱",
    "continent": "Europe",
    "lat": 52.1326,
    "lng": 5.2913,
    "currency": "EUR",
    "language": "Dutch",
    "data": {
      "id": "cd-004",
      "countryId": "nl-001",
      "salarySoftwareEngineer": 68000,
      "salaryNurse": 38000,
      "salaryTeacher": 45000,
      "salaryAccountant": 50000,
      "salaryMarketingManager": 58000,
      "costRentCityCentre": 1850,
      "costRentOutside": 1350,
      "costGroceriesMonthly": 360,
      "costTransportMonthly": 100,
      "costUtilitiesMonthly": 220,
      "costEatingOut": 18,
      "scoreQualityOfLife": 8.5,
      "scoreHealthcare": 8.6,
      "scoreSafety": 8.3,
      "scoreInternetSpeed": 8.8,
      "incomeTaxRateMid": 36.93,
      "socialSecurityRate": 27.65,
      "visaDifficulty": 2,
      "visaNotes": "The 30% ruling tax benefit makes the Netherlands very attractive for skilled expats — allowing 30% of gross salary tax-free for 5 years. The Highly Skilled Migrant visa is employer-sponsored with a minimum salary threshold (~€5,600/month gross). Note: the 30% ruling has been capped and is under ongoing review.",
      "visaPopularRoutes": [
        "Highly Skilled Migrant",
        "EU Blue Card",
        "Self-Employment"
      ],
      "visaOfficialUrl": "https://ind.nl/en",
      "moveScore": 7.4,
      "lastVerified": "2026-04-26"
    }
  },
  {
    "id": "pt-001",
    "slug": "portugal",
    "name": "Portugal",
    "flagEmoji": "🇵🇹",
    "continent": "Europe",
    "lat": 39.3999,
    "lng": -8.2245,
    "currency": "EUR",
    "language": "Portuguese",
    "data": {
      "id": "cd-005",
      "countryId": "pt-001",
      "salarySoftwareEngineer": 45000,
      "salaryNurse": 22000,
      "salaryTeacher": 25000,
      "salaryAccountant": 29000,
      "salaryMarketingManager": 37000,
      "costRentCityCentre": 1150,
      "costRentOutside": 800,
      "costGroceriesMonthly": 310,
      "costTransportMonthly": 45,
      "costUtilitiesMonthly": 145,
      "costEatingOut": 12,
      "scoreQualityOfLife": 8,
      "scoreHealthcare": 7.2,
      "scoreSafety": 9,
      "scoreInternetSpeed": 8.1,
      "incomeTaxRateMid": 28.5,
      "socialSecurityRate": 11,
      "visaDifficulty": 2,
      "visaNotes": "The D7 Passive Income Visa requires a minimum €920/month passive income in 2026 (indexed to Portugal's minimum wage). The D8 Digital Nomad Visa requires ~€3,480/month in remote income. Processing now runs through AIMA (replaced SEF) with wait times of 6–12 months for appointments. NHR 2.0 tax regime still available for qualifying new residents.",
      "visaPopularRoutes": [
        "D7 Passive Income Visa",
        "D8 Digital Nomad Visa",
        "Tech Visa (D3)"
      ],
      "visaOfficialUrl": "https://aima.gov.pt/en",
      "moveScore": 7.4,
      "lastVerified": "2026-04-26"
    }
  },
  {
    "id": "ie-001",
    "slug": "ireland",
    "name": "Ireland",
    "flagEmoji": "🇮🇪",
    "continent": "Europe",
    "lat": 53.1424,
    "lng": -7.6921,
    "currency": "EUR",
    "language": "English, Irish",
    "data": {
      "id": "cd-006",
      "countryId": "ie-001",
      "salarySoftwareEngineer": 78000,
      "salaryNurse": 42000,
      "salaryTeacher": 44000,
      "salaryAccountant": 52000,
      "salaryMarketingManager": 62000,
      "costRentCityCentre": 2450,
      "costRentOutside": 1800,
      "costGroceriesMonthly": 360,
      "costTransportMonthly": 130,
      "costUtilitiesMonthly": 200,
      "costEatingOut": 19,
      "scoreQualityOfLife": 8.2,
      "scoreHealthcare": 6.8,
      "scoreSafety": 8.4,
      "scoreInternetSpeed": 7.6,
      "incomeTaxRateMid": 40,
      "socialSecurityRate": 4,
      "visaDifficulty": 2,
      "visaNotes": "The Critical Skills Employment Permit is the main route for in-demand roles (tech, healthcare, engineering). English-speaking and home to European HQs of major US tech firms. Dublin rents have risen sharply — budget €2,400+ for a 1BR in the city centre. General Work Permit available for other occupations.",
      "visaPopularRoutes": [
        "Critical Skills Employment Permit",
        "General Work Permit",
        "Stamp 4"
      ],
      "visaOfficialUrl": "https://www.irishimmigration.ie/",
      "moveScore": 7,
      "lastVerified": "2026-04-26"
    }
  },
  {
    "id": "gb-001",
    "slug": "united-kingdom",
    "name": "United Kingdom",
    "flagEmoji": "🇬🇧",
    "continent": "Europe",
    "lat": 55.3781,
    "lng": -3.436,
    "currency": "GBP",
    "language": "English",
    "data": {
      "id": "cd-007",
      "countryId": "gb-001",
      "salarySoftwareEngineer": 72000,
      "salaryNurse": 36000,
      "salaryTeacher": 39000,
      "salaryAccountant": 50000,
      "salaryMarketingManager": 57000,
      "costRentCityCentre": 2300,
      "costRentOutside": 1600,
      "costGroceriesMonthly": 330,
      "costTransportMonthly": 165,
      "costUtilitiesMonthly": 200,
      "costEatingOut": 17,
      "scoreQualityOfLife": 7.8,
      "scoreHealthcare": 7.5,
      "scoreSafety": 7.6,
      "scoreInternetSpeed": 7.8,
      "incomeTaxRateMid": 40,
      "socialSecurityRate": 12,
      "visaDifficulty": 3,
      "visaNotes": "The Skilled Worker visa requires employer sponsorship and a minimum salary of £41,700 (as of July 2025) for most roles, or the going rate for your occupation code, whichever is higher. Minimum skill level raised to RQF Level 6 (degree-equivalent) in July 2025. Global Talent visa available without a job offer for exceptional candidates.",
      "visaPopularRoutes": [
        "Skilled Worker Visa",
        "Global Talent Visa",
        "Scale-Up Visa"
      ],
      "visaOfficialUrl": "https://www.gov.uk/browse/visas-immigration",
      "moveScore": 6.8,
      "lastVerified": "2026-04-26"
    }
  },
  {
    "id": "ae-001",
    "slug": "uae",
    "name": "UAE",
    "flagEmoji": "🇦🇪",
    "continent": "Asia",
    "lat": 23.4241,
    "lng": 53.8478,
    "currency": "AED",
    "language": "Arabic, English",
    "data": {
      "id": "cd-008",
      "countryId": "ae-001",
      "salarySoftwareEngineer": 88000,
      "salaryNurse": 46000,
      "salaryTeacher": 43000,
      "salaryAccountant": 56000,
      "salaryMarketingManager": 67000,
      "costRentCityCentre": 1900,
      "costRentOutside": 1300,
      "costGroceriesMonthly": 410,
      "costTransportMonthly": 100,
      "costUtilitiesMonthly": 155,
      "costEatingOut": 13,
      "scoreQualityOfLife": 7.5,
      "scoreHealthcare": 7.8,
      "scoreSafety": 9.2,
      "scoreInternetSpeed": 8.5,
      "incomeTaxRateMid": 0,
      "socialSecurityRate": 0,
      "visaDifficulty": 2,
      "visaNotes": "Zero income tax remains the biggest draw. The 10-year Golden Visa expanded in 2025–2026 to include content creators, educators, nurses with 15+ years service, and e-sports professionals, alongside investors (AED 2M) and skilled professionals. The Feb 2026 update removed the 50% down payment requirement for property investors. Standard employment visas remain fast to process via employer sponsorship.",
      "visaPopularRoutes": [
        "Employment Visa",
        "Golden Visa (10-year)",
        "Freelancer Visa"
      ],
      "visaOfficialUrl": "https://icp.gov.ae/en/",
      "moveScore": 8.1,
      "lastVerified": "2026-04-26"
    }
  },
  {
    "id": "nz-001",
    "slug": "new-zealand",
    "name": "New Zealand",
    "flagEmoji": "🇳🇿",
    "continent": "Oceania",
    "lat": -40.9006,
    "lng": 174.886,
    "currency": "NZD",
    "language": "English, Maori",
    "data": {
      "id": "cd-009",
      "countryId": "nz-001",
      "salarySoftwareEngineer": 85000,
      "salaryNurse": 60000,
      "salaryTeacher": 54000,
      "salaryAccountant": 62000,
      "salaryMarketingManager": 72000,
      "costRentCityCentre": 1700,
      "costRentOutside": 1250,
      "costGroceriesMonthly": 390,
      "costTransportMonthly": 110,
      "costUtilitiesMonthly": 175,
      "costEatingOut": 20,
      "scoreQualityOfLife": 8.6,
      "scoreHealthcare": 7.5,
      "scoreSafety": 8.8,
      "scoreInternetSpeed": 7,
      "incomeTaxRateMid": 30,
      "socialSecurityRate": 0,
      "visaDifficulty": 3,
      "visaNotes": "The Accredited Employer Work Visa (AEWV) is the main employer-sponsored route. The Green List offers fast-track residency for in-demand occupations (nurses, teachers, engineers). Beautiful lifestyle but remote location adds travel cost and adjustment time.",
      "visaPopularRoutes": [
        "Accredited Employer Work Visa",
        "Green List Residence",
        "Working Holiday"
      ],
      "visaOfficialUrl": "https://www.immigration.govt.nz/",
      "moveScore": 7.3,
      "lastVerified": "2026-04-26"
    }
  },
  {
    "id": "es-001",
    "slug": "spain",
    "name": "Spain",
    "flagEmoji": "🇪🇸",
    "continent": "Europe",
    "lat": 40.4637,
    "lng": -3.7492,
    "currency": "EUR",
    "language": "Spanish",
    "data": {
      "id": "cd-010",
      "countryId": "es-001",
      "salarySoftwareEngineer": 46000,
      "salaryNurse": 28000,
      "salaryTeacher": 31000,
      "salaryAccountant": 33000,
      "salaryMarketingManager": 41000,
      "costRentCityCentre": 1200,
      "costRentOutside": 820,
      "costGroceriesMonthly": 290,
      "costTransportMonthly": 50,
      "costUtilitiesMonthly": 140,
      "costEatingOut": 13,
      "scoreQualityOfLife": 8.3,
      "scoreHealthcare": 8,
      "scoreSafety": 8.2,
      "scoreInternetSpeed": 7.5,
      "incomeTaxRateMid": 30,
      "socialSecurityRate": 6.35,
      "visaDifficulty": 2,
      "visaNotes": "The Digital Nomad Visa (launched 2023) is popular for remote workers requiring ~€2,334/month income and applying through a Spanish consulate. The Beckham Law offers a flat 24% income tax rate for up to 6 years. Non-lucrative visa suits retirees and passive income earners. Barcelona and Madrid rents rising but still below Dublin/London.",
      "visaPopularRoutes": [
        "Digital Nomad Visa",
        "Non-Lucrative Visa",
        "EU Blue Card"
      ],
      "visaOfficialUrl": "https://www.exteriores.gob.es/en/",
      "moveScore": 7.4,
      "lastVerified": "2026-04-26"
    }
  },
  {
    "id": "se-001",
    "slug": "sweden",
    "name": "Sweden",
    "flagEmoji": "🇸🇪",
    "continent": "Europe",
    "lat": 60.1282,
    "lng": 18.6435,
    "currency": "SEK",
    "language": "Swedish",
    "data": {
      "id": "cd-011",
      "countryId": "se-001",
      "salarySoftwareEngineer": 63000,
      "salaryNurse": 39000,
      "salaryTeacher": 41000,
      "salaryAccountant": 46000,
      "salaryMarketingManager": 53000,
      "costRentCityCentre": 1250,
      "costRentOutside": 880,
      "costGroceriesMonthly": 330,
      "costTransportMonthly": 90,
      "costUtilitiesMonthly": 110,
      "costEatingOut": 15,
      "scoreQualityOfLife": 8.8,
      "scoreHealthcare": 8.5,
      "scoreSafety": 7.8,
      "scoreInternetSpeed": 8.9,
      "incomeTaxRateMid": 52,
      "socialSecurityRate": 7,
      "visaDifficulty": 2,
      "visaNotes": "Work permit requires a job offer. The employer must advertise the role in the EU/EEA for 10 days and offer market-rate salary with full benefits. Sweden offers excellent work-life balance, generous parental leave, and strong public services. High taxes are offset by free healthcare and education.",
      "visaPopularRoutes": [
        "Work Permit",
        "EU Blue Card",
        "Self-Employment Permit"
      ],
      "visaOfficialUrl": "https://www.migrationsverket.se/English.html",
      "moveScore": 6.9,
      "lastVerified": "2026-04-26"
    }
  },
  {
    "id": "ch-001",
    "slug": "switzerland",
    "name": "Switzerland",
    "flagEmoji": "🇨🇭",
    "continent": "Europe",
    "lat": 46.8182,
    "lng": 8.2275,
    "currency": "CHF",
    "language": "German, French, Italian",
    "data": {
      "id": "cd-012",
      "countryId": "ch-001",
      "salarySoftwareEngineer": 130000,
      "salaryNurse": 75000,
      "salaryTeacher": 85000,
      "salaryAccountant": 90000,
      "salaryMarketingManager": 100000,
      "costRentCityCentre": 2900,
      "costRentOutside": 2100,
      "costGroceriesMonthly": 520,
      "costTransportMonthly": 85,
      "costUtilitiesMonthly": 260,
      "costEatingOut": 32,
      "scoreQualityOfLife": 9.2,
      "scoreHealthcare": 9.1,
      "scoreSafety": 9.3,
      "scoreInternetSpeed": 8.7,
      "incomeTaxRateMid": 22,
      "socialSecurityRate": 6.4,
      "visaDifficulty": 4,
      "visaNotes": "Very restrictive immigration for non-EU nationals. Employers must prove no suitable EU/EFTA candidate is available before sponsoring from outside the EU. Annual quotas apply. L-permit (short-term, up to 1 year) and B-permit (residence, renewable) are the main work permits. Salaries are the highest in Europe but costs are proportionally high.",
      "visaPopularRoutes": [
        "L-Permit",
        "B-Permit",
        "EU/EFTA Free Movement"
      ],
      "visaOfficialUrl": "https://www.sem.admin.ch/sem/en/home.html",
      "moveScore": 7.6,
      "lastVerified": "2026-04-26"
    }
  },
  {
    "id": "sg-001",
    "slug": "singapore",
    "name": "Singapore",
    "flagEmoji": "🇸🇬",
    "continent": "Asia",
    "lat": 1.3521,
    "lng": 103.8198,
    "currency": "SGD",
    "language": "English, Mandarin, Malay, Tamil",
    "data": {
      "id": "cd-013",
      "countryId": "sg-001",
      "salarySoftwareEngineer": 92000,
      "salaryNurse": 42000,
      "salaryTeacher": 52000,
      "salaryAccountant": 57000,
      "salaryMarketingManager": 67000,
      "costRentCityCentre": 2900,
      "costRentOutside": 1900,
      "costGroceriesMonthly": 360,
      "costTransportMonthly": 80,
      "costUtilitiesMonthly": 130,
      "costEatingOut": 9,
      "scoreQualityOfLife": 8.3,
      "scoreHealthcare": 8.8,
      "scoreSafety": 9.5,
      "scoreInternetSpeed": 9.2,
      "incomeTaxRateMid": 7,
      "socialSecurityRate": 20,
      "visaDifficulty": 3,
      "visaNotes": "Employment Pass (EP) is the main route for professionals — minimum salary raised to SGD 5,600/month in 2025 for most sectors (SGD 6,200 for finance). The COMPASS framework adds a points-based scoring element. Low tax rates and world-class infrastructure are major draws, though rents remain very high.",
      "visaPopularRoutes": [
        "Employment Pass (EP)",
        "S Pass",
        "EntrePass"
      ],
      "visaOfficialUrl": "https://www.mom.gov.sg/passes-and-permits",
      "moveScore": 7.9,
      "lastVerified": "2026-04-26"
    }
  },
  {
    "id": "us-001",
    "slug": "usa",
    "name": "USA",
    "flagEmoji": "🇺🇸",
    "continent": "North America",
    "lat": 37.0902,
    "lng": -95.7129,
    "currency": "USD",
    "language": "English",
    "data": {
      "id": "cd-014",
      "countryId": "us-001",
      "salarySoftwareEngineer": 140000,
      "salaryNurse": 82000,
      "salaryTeacher": 60000,
      "salaryAccountant": 72000,
      "salaryMarketingManager": 95000,
      "costRentCityCentre": 2600,
      "costRentOutside": 1900,
      "costGroceriesMonthly": 400,
      "costTransportMonthly": 120,
      "costUtilitiesMonthly": 185,
      "costEatingOut": 20,
      "scoreQualityOfLife": 7.4,
      "scoreHealthcare": 6.5,
      "scoreSafety": 6.8,
      "scoreInternetSpeed": 8,
      "incomeTaxRateMid": 24,
      "socialSecurityRate": 7.65,
      "visaDifficulty": 4,
      "visaNotes": "H-1B visa is lottery-based with an annual cap of 85,000 — odds around 30% for a single entry. L-1 intracompany transfer is the most reliable route for those already working for a US company abroad. O-1 is available for extraordinary ability. Highest tech salaries globally but immigration uncertainty remains high.",
      "visaPopularRoutes": [
        "H-1B Visa",
        "L-1 Transfer",
        "O-1 Extraordinary Ability"
      ],
      "visaOfficialUrl": "https://www.uscis.gov/",
      "moveScore": 7.2,
      "lastVerified": "2026-04-26"
    }
  },
  {
    "id": "no-001",
    "slug": "norway",
    "name": "Norway",
    "flagEmoji": "🇳🇴",
    "continent": "Europe",
    "lat": 60.472,
    "lng": 8.4689,
    "currency": "NOK",
    "language": "Norwegian",
    "data": {
      "id": "cd-015",
      "countryId": "no-001",
      "salarySoftwareEngineer": 80000,
      "salaryNurse": 56000,
      "salaryTeacher": 54000,
      "salaryAccountant": 62000,
      "salaryMarketingManager": 67000,
      "costRentCityCentre": 1550,
      "costRentOutside": 1150,
      "costGroceriesMonthly": 420,
      "costTransportMonthly": 80,
      "costUtilitiesMonthly": 185,
      "costEatingOut": 23,
      "scoreQualityOfLife": 9,
      "scoreHealthcare": 8.7,
      "scoreSafety": 9.1,
      "scoreInternetSpeed": 8.5,
      "incomeTaxRateMid": 34,
      "socialSecurityRate": 7.8,
      "visaDifficulty": 3,
      "visaNotes": "Skilled Worker permit requires a concrete job offer and proof of qualifications. Norway is not in the EU but in the EEA — non-EEA nationals face a full immigration process. Excellent welfare state and quality of life, but the language barrier is real and costs are among the highest in Europe.",
      "visaPopularRoutes": [
        "Skilled Worker Permit",
        "Job Seeker Visa",
        "Self-Employment"
      ],
      "visaOfficialUrl": "https://www.udi.no/en/",
      "moveScore": 7.5,
      "lastVerified": "2026-04-26"
    }
  },
  {
    "id": "fr-001",
    "slug": "france",
    "name": "France",
    "flagEmoji": "🇫🇷",
    "continent": "Europe",
    "lat": 46.2276,
    "lng": 2.2137,
    "currency": "EUR",
    "language": "French",
    "data": {
      "id": "cd-016",
      "countryId": "fr-001",
      "salarySoftwareEngineer": 55000,
      "salaryNurse": 32000,
      "salaryTeacher": 34000,
      "salaryAccountant": 40000,
      "salaryMarketingManager": 50000,
      "costRentCityCentre": 1400,
      "costRentOutside": 950,
      "costGroceriesMonthly": 320,
      "costTransportMonthly": 85,
      "costUtilitiesMonthly": 160,
      "costEatingOut": 15,
      "scoreQualityOfLife": 8,
      "scoreHealthcare": 8.5,
      "scoreSafety": 7.5,
      "scoreInternetSpeed": 7.8,
      "incomeTaxRateMid": 30,
      "socialSecurityRate": 22,
      "visaDifficulty": 2,
      "visaNotes": "The Talent Passport (Passeport Talent) covers multiple categories including employees of innovative companies, researchers, and startup founders. Requires a job offer or proof of eligibility. French language skills greatly help integration. Paris is expensive but other cities like Lyon and Bordeaux offer a good lifestyle-to-cost ratio.",
      "visaPopularRoutes": [
        "Talent Passport",
        "EU Blue Card",
        "Work Permit (Salarié)"
      ],
      "visaOfficialUrl": "https://www.service-public.fr/particuliers/vosdroits/N19804",
      "moveScore": 7,
      "lastVerified": "2026-04-26"
    }
  },
  {
    "id": "jp-001",
    "slug": "japan",
    "name": "Japan",
    "flagEmoji": "🇯🇵",
    "continent": "Asia",
    "lat": 36.2048,
    "lng": 138.2529,
    "currency": "JPY",
    "language": "Japanese",
    "data": {
      "id": "cd-017",
      "countryId": "jp-001",
      "salarySoftwareEngineer": 6500000,
      "salaryNurse": 4000000,
      "salaryTeacher": 4200000,
      "salaryAccountant": 5000000,
      "salaryMarketingManager": 6000000,
      "costRentCityCentre": 120000,
      "costRentOutside": 80000,
      "costGroceriesMonthly": 35000,
      "costTransportMonthly": 12000,
      "costUtilitiesMonthly": 12000,
      "costEatingOut": 1200,
      "scoreQualityOfLife": 8.2,
      "scoreHealthcare": 8.8,
      "scoreSafety": 9.4,
      "scoreInternetSpeed": 8.6,
      "incomeTaxRateMid": 33,
      "socialSecurityRate": 14,
      "visaDifficulty": 3,
      "visaNotes": "Engineer/Specialist Humanities visa is the main route for tech and professional workers — requires a job offer and relevant degree. The Highly Skilled Professional points system offers fast-track permanent residence in as little as 1–3 years. Japanese language proficiency greatly improves quality of life. Remote-work infrastructure is growing but Japan remains more traditional in workplace culture.",
      "visaPopularRoutes": [
        "Engineer/Specialist Humanities Visa",
        "Highly Skilled Professional (HSP)",
        "Startup Visa"
      ],
      "visaOfficialUrl": "https://www.isa.go.jp/en/",
      "moveScore": 7.2,
      "lastVerified": "2026-04-26"
    }
  },
  {
    "id": "it-001",
    "slug": "italy",
    "name": "Italy",
    "flagEmoji": "🇮🇹",
    "continent": "Europe",
    "lat": 41.8719,
    "lng": 12.5674,
    "currency": "EUR",
    "language": "Italian",
    "data": {
      "id": "cd-018",
      "countryId": "it-001",
      "salarySoftwareEngineer": 42000,
      "salaryNurse": 27000,
      "salaryTeacher": 28000,
      "salaryAccountant": 32000,
      "salaryMarketingManager": 38000,
      "costRentCityCentre": 1100,
      "costRentOutside": 750,
      "costGroceriesMonthly": 280,
      "costTransportMonthly": 45,
      "costUtilitiesMonthly": 160,
      "costEatingOut": 13,
      "scoreQualityOfLife": 8,
      "scoreHealthcare": 7.8,
      "scoreSafety": 7.9,
      "scoreInternetSpeed": 6.8,
      "incomeTaxRateMid": 38,
      "socialSecurityRate": 9.19,
      "visaDifficulty": 3,
      "visaNotes": "The Decreto Flussi annual quota system controls non-EU work permits and can be competitive. The Intra-company transfer and EU Blue Card routes are more straightforward. Italy offers a Flat Tax regime (€100k/year flat tax) for high-income new residents, and a 70% income tax exemption for new workers who transfer their residency to Italy.",
      "visaPopularRoutes": [
        "EU Blue Card",
        "Intra-Company Transfer",
        "Elective Residency Visa"
      ],
      "visaOfficialUrl": "https://vistoperitalia.esteri.it/home/en",
      "moveScore": 6.8,
      "lastVerified": "2026-04-26"
    }
  },
  {
    "id": "at-001",
    "slug": "austria",
    "name": "Austria",
    "flagEmoji": "🇦🇹",
    "continent": "Europe",
    "lat": 47.5162,
    "lng": 14.5501,
    "currency": "EUR",
    "language": "German",
    "data": {
      "id": "cd-019",
      "countryId": "at-001",
      "salarySoftwareEngineer": 58000,
      "salaryNurse": 38000,
      "salaryTeacher": 40000,
      "salaryAccountant": 45000,
      "salaryMarketingManager": 52000,
      "costRentCityCentre": 1200,
      "costRentOutside": 850,
      "costGroceriesMonthly": 310,
      "costTransportMonthly": 55,
      "costUtilitiesMonthly": 200,
      "costEatingOut": 14,
      "scoreQualityOfLife": 8.6,
      "scoreHealthcare": 8.5,
      "scoreSafety": 8.8,
      "scoreInternetSpeed": 7.4,
      "incomeTaxRateMid": 42,
      "socialSecurityRate": 18.12,
      "visaDifficulty": 3,
      "visaNotes": "The Red-White-Red Card is Austria's main skilled immigration route — a points-based system for skilled workers, key personnel, and graduates from Austrian universities. Requires a job offer meeting salary thresholds. Vienna consistently ranks as the world's most liveable city. German language skills are essential for daily life.",
      "visaPopularRoutes": [
        "Red-White-Red Card",
        "EU Blue Card",
        "Intra-Company Transfer"
      ],
      "visaOfficialUrl": "https://www.migration.gv.at/en/",
      "moveScore": 7.3,
      "lastVerified": "2026-04-26"
    }
  },
  {
    "id": "be-001",
    "slug": "belgium",
    "name": "Belgium",
    "flagEmoji": "🇧🇪",
    "continent": "Europe",
    "lat": 50.5039,
    "lng": 4.4699,
    "currency": "EUR",
    "language": "Dutch, French, German",
    "data": {
      "id": "cd-020",
      "countryId": "be-001",
      "salarySoftwareEngineer": 60000,
      "salaryNurse": 38000,
      "salaryTeacher": 40000,
      "salaryAccountant": 46000,
      "salaryMarketingManager": 54000,
      "costRentCityCentre": 1200,
      "costRentOutside": 850,
      "costGroceriesMonthly": 320,
      "costTransportMonthly": 55,
      "costUtilitiesMonthly": 200,
      "costEatingOut": 16,
      "scoreQualityOfLife": 7.9,
      "scoreHealthcare": 8.2,
      "scoreSafety": 7.6,
      "scoreInternetSpeed": 8,
      "incomeTaxRateMid": 45,
      "socialSecurityRate": 13.07,
      "visaDifficulty": 2,
      "visaNotes": "Single Permit combines a work and residence permit for non-EU nationals. Requires a job offer with a salary meeting regional thresholds. Belgium is home to EU institutions which drives multilingual demand. High taxes are a significant downside, though net salaries remain competitive. Expat tax regime available for some.",
      "visaPopularRoutes": [
        "Single Permit",
        "EU Blue Card",
        "Highly Qualified Worker"
      ],
      "visaOfficialUrl": "https://dofi.ibz.be/en",
      "moveScore": 6.9,
      "lastVerified": "2026-04-26"
    }
  },
  {
    "id": "dk-001",
    "slug": "denmark",
    "name": "Denmark",
    "flagEmoji": "🇩🇰",
    "continent": "Europe",
    "lat": 56.2639,
    "lng": 9.5018,
    "currency": "DKK",
    "language": "Danish",
    "data": {
      "id": "cd-021",
      "countryId": "dk-001",
      "salarySoftwareEngineer": 580000,
      "salaryNurse": 400000,
      "salaryTeacher": 420000,
      "salaryAccountant": 460000,
      "salaryMarketingManager": 520000,
      "costRentCityCentre": 14000,
      "costRentOutside": 9500,
      "costGroceriesMonthly": 3200,
      "costTransportMonthly": 450,
      "costUtilitiesMonthly": 1400,
      "costEatingOut": 160,
      "scoreQualityOfLife": 9,
      "scoreHealthcare": 8.6,
      "scoreSafety": 8.9,
      "scoreInternetSpeed": 9,
      "incomeTaxRateMid": 55,
      "socialSecurityRate": 8,
      "visaDifficulty": 2,
      "visaNotes": "The Pay Limit Scheme allows high-earning professionals (DKK 500,000+/year) to obtain a work permit without labour market testing. The Positive List scheme covers in-demand occupations. Denmark has one of the best work-life balances in the world. High taxes fund excellent public services including free healthcare and education.",
      "visaPopularRoutes": [
        "Pay Limit Scheme",
        "Positive List",
        "EU Blue Card"
      ],
      "visaOfficialUrl": "https://www.nyidanmark.dk/en-GB",
      "moveScore": 7.2,
      "lastVerified": "2026-04-26"
    }
  },
  {
    "id": "fi-001",
    "slug": "finland",
    "name": "Finland",
    "flagEmoji": "🇫🇮",
    "continent": "Europe",
    "lat": 61.9241,
    "lng": 25.7482,
    "currency": "EUR",
    "language": "Finnish, Swedish",
    "data": {
      "id": "cd-022",
      "countryId": "fi-001",
      "salarySoftwareEngineer": 60000,
      "salaryNurse": 38000,
      "salaryTeacher": 40000,
      "salaryAccountant": 44000,
      "salaryMarketingManager": 50000,
      "costRentCityCentre": 1100,
      "costRentOutside": 780,
      "costGroceriesMonthly": 320,
      "costTransportMonthly": 75,
      "costUtilitiesMonthly": 160,
      "costEatingOut": 15,
      "scoreQualityOfLife": 9.1,
      "scoreHealthcare": 8.4,
      "scoreSafety": 9.2,
      "scoreInternetSpeed": 8.8,
      "incomeTaxRateMid": 44,
      "socialSecurityRate": 8.4,
      "visaDifficulty": 2,
      "visaNotes": "Finland's D permit (employed) is the main route for non-EU workers — requires a job offer and employer registration. The Fast Track service for specialist workers cuts processing to around 2 weeks. Finland actively recruits tech and healthcare talent and offers strong startup ecosystem support. Finnish language is challenging but English is widely spoken.",
      "visaPopularRoutes": [
        "Employed Person's Residence Permit (D)",
        "EU Blue Card",
        "Startup Permit"
      ],
      "visaOfficialUrl": "https://migri.fi/en/",
      "moveScore": 7.1,
      "lastVerified": "2026-04-26"
    }
  },
  {
    "id": "my-001",
    "slug": "malaysia",
    "name": "Malaysia",
    "flagEmoji": "🇲🇾",
    "continent": "Asia",
    "lat": 4.2105,
    "lng": 101.9758,
    "currency": "MYR",
    "language": "Malay, English",
    "data": {
      "id": "cd-023",
      "countryId": "my-001",
      "salarySoftwareEngineer": 90000,
      "salaryNurse": 36000,
      "salaryTeacher": 36000,
      "salaryAccountant": 48000,
      "salaryMarketingManager": 60000,
      "costRentCityCentre": 2500,
      "costRentOutside": 1500,
      "costGroceriesMonthly": 700,
      "costTransportMonthly": 150,
      "costUtilitiesMonthly": 400,
      "costEatingOut": 30,
      "scoreQualityOfLife": 7.2,
      "scoreHealthcare": 7,
      "scoreSafety": 7,
      "scoreInternetSpeed": 7.6,
      "incomeTaxRateMid": 21,
      "socialSecurityRate": 0,
      "visaDifficulty": 2,
      "visaNotes": "Malaysia My Second Home (MM2H) programme offers long-term residency for qualifying applicants. Employment Pass for professionals requires employer sponsorship. Kuala Lumpur offers a very low cost of living for expats with strong English proficiency and a multicultural environment. Tech hub growing rapidly.",
      "visaPopularRoutes": [
        "Employment Pass",
        "Malaysia My Second Home (MM2H)",
        "Professional Visit Pass"
      ],
      "visaOfficialUrl": "https://www.imi.gov.my/",
      "moveScore": 7.1,
      "lastVerified": "2026-04-26"
    }
  },
  {
    "id": "in-001",
    "slug": "india",
    "name": "India",
    "flagEmoji": "🇮🇳",
    "continent": "Asia",
    "lat": 20.5937,
    "lng": 78.9629,
    "currency": "INR",
    "language": "Hindi, English",
    "data": {
      "id": "cd-024",
      "countryId": "in-001",
      "salarySoftwareEngineer": 2200000,
      "salaryNurse": 480000,
      "salaryTeacher": 500000,
      "salaryAccountant": 700000,
      "salaryMarketingManager": 1200000,
      "costRentCityCentre": 30000,
      "costRentOutside": 18000,
      "costGroceriesMonthly": 8000,
      "costTransportMonthly": 3000,
      "costUtilitiesMonthly": 5000,
      "costEatingOut": 300,
      "scoreQualityOfLife": 5.8,
      "scoreHealthcare": 5.5,
      "scoreSafety": 5.5,
      "scoreInternetSpeed": 6.5,
      "incomeTaxRateMid": 30,
      "socialSecurityRate": 12,
      "visaDifficulty": 2,
      "visaNotes": "Employment Visa required for foreign nationals working in India — employer must be registered and the role typically requires specialised skills not locally available. India is primarily a source of outbound expats rather than inbound. Moving to India suits those with cultural ties, entrepreneurial ambitions, or regional business roles. Fast-growing startup ecosystem in Bangalore, Hyderabad, and Mumbai.",
      "visaPopularRoutes": [
        "Employment Visa",
        "Business Visa",
        "Entrepreneur Visa"
      ],
      "visaOfficialUrl": "https://www.indianvisaonline.gov.in/",
      "moveScore": 5.5,
      "lastVerified": "2026-04-26"
    }
  },
  {
    "id": "br-001",
    "slug": "brazil",
    "name": "Brazil",
    "flagEmoji": "🇧🇷",
    "continent": "South America",
    "lat": -14.235,
    "lng": -51.9253,
    "currency": "BRL",
    "language": "Portuguese",
    "data": {
      "id": "cd-025",
      "countryId": "br-001",
      "salarySoftwareEngineer": 120000,
      "salaryNurse": 38000,
      "salaryTeacher": 36000,
      "salaryAccountant": 55000,
      "salaryMarketingManager": 80000,
      "costRentCityCentre": 3500,
      "costRentOutside": 2200,
      "costGroceriesMonthly": 1200,
      "costTransportMonthly": 250,
      "costUtilitiesMonthly": 600,
      "costEatingOut": 35,
      "scoreQualityOfLife": 6.2,
      "scoreHealthcare": 6,
      "scoreSafety": 5,
      "scoreInternetSpeed": 6.8,
      "incomeTaxRateMid": 27.5,
      "socialSecurityRate": 11,
      "visaDifficulty": 2,
      "visaNotes": "Brazil offers a Digital Nomad Visa for remote workers earning at least USD 1,500/month, valid for 1 year and renewable. Work permits for employed foreigners require employer sponsorship and approval from the Ministry of Labour. Brazil has a large and vibrant expat community in São Paulo and Rio, but safety concerns vary significantly by neighbourhood.",
      "visaPopularRoutes": [
        "Digital Nomad Visa",
        "Work Permit (CTPS)",
        "Retirement Visa"
      ],
      "visaOfficialUrl": "https://www.gov.br/mre/en/topics/visas",
      "moveScore": 5.8,
      "lastVerified": "2026-04-26"
    }
  }
]